{
  "tree_models": {
    "dataset_type": "tree_models",
    "categorical_features": [
      "gics_sector",
      "gics_sub_ind",
      "issuer_cntry_domicile_name",
      "cntry_of_risk",
      "top_1_shareholder_location",
      "top_2_shareholder_location",
      "top_3_shareholder_location"
    ],
    "original_shape": [
      2202,
      34
    ],
    "tree_dataset_shape": [
      2202,
      34
    ],
    "nan_count": "0"
  },
  "linear_models": {
    "dataset_type": "linear_models",
    "encoding_type": "one_hot",
    "dataset_shape": [
      2202,
      389
    ],
    "note": "Original one-hot encoded dataset for ElasticNet and Linear Regression"
  },
  "creation_timestamp": "2025-06-19T21:03:18.734147",
  "description": "Separate datasets for tree-based and linear models with optimal feature encoding"
}